setup.py
scratch_dsnd_probalility/Binomialdistribution.py
scratch_dsnd_probalility/Gaussiandistribution.py
scratch_dsnd_probalility/Generaldistribution.py
scratch_dsnd_probalility/__init__.py
scratch_dsnd_probalility.egg-info/PKG-INFO
scratch_dsnd_probalility.egg-info/SOURCES.txt
scratch_dsnd_probalility.egg-info/dependency_links.txt
scratch_dsnd_probalility.egg-info/not-zip-safe
scratch_dsnd_probalility.egg-info/top_level.txt