Metadata-Version: 1.0
Name: scratch-dsnd-probalility
Version: 1.0
Summary: Gaussian and Binomial distributions
Home-page: UNKNOWN
Author: Ayité Mawussé HILLAH
Author-email: mawusseayite@outlook.fr
License: UNKNOWN
Platform: UNKNOWN
